IP2Location.py
ip2l-8.5.1.dist-info/AUTHORS
ip2l-8.5.1.dist-info/LICENSE.TXT
ip2l-8.5.1.dist-info/METADATA
ip2l-8.5.1.dist-info/WHEEL
ip2l-8.5.1.dist-info/top_level.txt
ip2l-8.5.1.dist-info/RECORD
