Metadata-Version: 2.1
Name: ip2l
Version: 8.5.1
Summary: Python API for IP2Location database.
Home-page: https://github.com/ip2location/ip2location-python
Author: pytool
Author-email: pytli@pytool.com
License: UNKNOWN
Platform: UNKNOWN
Classifier: Development Status :: 5 - Production/Stable
Classifier: Intended Audience :: Developers
Classifier: Topic :: Software Development :: Libraries :: Python Modules
Classifier: Programming Language :: Python :: 2.7
Classifier: Programming Language :: Python :: 3
Classifier: License :: OSI Approved :: MIT License
Classifier: Operating System :: OS Independent
Requires-Dist: Django (!=1.11.1,<=2,>=1.11)
